{
  "id": "Nest.ICatResponse`1[[Nest.CatNodesRecord, Nest, Version=1.0.0.0, Culture=neutral, PublicKeyToken=null]]",
  "$schema": "http://json-schema.org/draft-04/schema#",
  "title": "ICatResponse`1",
  "type": "object",
  "properties": {
    "records": {
      "id": "System.Collections.Generic.IEnumerable`1[[Nest.CatNodesRecord, Nest, Version=1.0.0.0, Culture=neutral, PublicKeyToken=null]]",
      "type": [
        "array",
        "null"
      ],
      "items": {
        "id": "Nest.CatNodesRecord",
        "type": [
          "object",
          "null"
        ],
        "properties": {
          "id": {
            "type": [
              "string",
              "null"
            ]
          },
          "nodeId": {
            "type": [
              "string",
              "null"
            ]
          },
          "pid": {
            "type": [
              "string",
              "null"
            ]
          },
          "p": {
            "type": [
              "string",
              "null"
            ]
          },
          "host": {
            "type": [
              "string",
              "null"
            ]
          },
          "h": {
            "type": [
              "string",
              "null"
            ]
          },
          "ip": {
            "type": [
              "string",
              "null"
            ]
          },
          "i": {
            "type": [
              "string",
              "null"
            ]
          },
          "port": {
            "type": [
              "string",
              "null"
            ]
          },
          "po": {
            "type": [
              "string",
              "null"
            ]
          },
          "version": {
            "type": [
              "string",
              "null"
            ]
          },
          "v": {
            "type": [
              "string",
              "null"
            ]
          },
          "build": {
            "type": [
              "string",
              "null"
            ]
          },
          "b": {
            "type": [
              "string",
              "null"
            ]
          },
          "jdk": {
            "type": [
              "string",
              "null"
            ]
          },
          "j": {
            "type": [
              "string",
              "null"
            ]
          },
          "disk.avail": {
            "type": [
              "string",
              "null"
            ]
          },
          "d": {
            "type": [
              "string",
              "null"
            ]
          },
          "disk": {
            "type": [
              "string",
              "null"
            ]
          },
          "diskAvail": {
            "type": [
              "string",
              "null"
            ]
          },
          "heap.percent": {
            "type": [
              "string",
              "null"
            ]
          },
          "hp": {
            "type": [
              "string",
              "null"
            ]
          },
          "heapPercent": {
            "type": [
              "string",
              "null"
            ]
          },
          "heap.max": {
            "type": [
              "string",
              "null"
            ]
          },
          "hm": {
            "type": [
              "string",
              "null"
            ]
          },
          "heapMax": {
            "type": [
              "string",
              "null"
            ]
          },
          "ram.percent": {
            "type": [
              "string",
              "null"
            ]
          },
          "rp": {
            "type": [
              "string",
              "null"
            ]
          },
          "ramPercent": {
            "type": [
              "string",
              "null"
            ]
          },
          "ram.max": {
            "type": [
              "string",
              "null"
            ]
          },
          "rm": {
            "type": [
              "string",
              "null"
            ]
          },
          "ramMax": {
            "type": [
              "string",
              "null"
            ]
          },
          "load": {
            "type": [
              "string",
              "null"
            ]
          },
          "l": {
            "type": [
              "string",
              "null"
            ]
          },
          "uptime": {
            "type": [
              "string",
              "null"
            ]
          },
          "u": {
            "type": [
              "string",
              "null"
            ]
          },
          "node.role": {
            "type": [
              "string",
              "null"
            ]
          },
          "r": {
            "type": [
              "string",
              "null"
            ]
          },
          "dc": {
            "type": [
              "string",
              "null"
            ]
          },
          "data/client": {
            "type": [
              "string",
              "null"
            ]
          },
          "nodeRole": {
            "type": [
              "string",
              "null"
            ]
          },
          "master": {
            "type": [
              "string",
              "null"
            ]
          },
          "m": {
            "type": [
              "string",
              "null"
            ]
          },
          "name": {
            "type": [
              "string",
              "null"
            ]
          },
          "n": {
            "type": [
              "string",
              "null"
            ]
          },
          "completion.size": {
            "type": [
              "string",
              "null"
            ]
          },
          "cs": {
            "type": [
              "string",
              "null"
            ]
          },
          "completionSize": {
            "type": [
              "string",
              "null"
            ]
          },
          "fielddata.memory_size": {
            "type": [
              "string",
              "null"
            ]
          },
          "fm": {
            "type": [
              "string",
              "null"
            ]
          },
          "fielddataMemory": {
            "type": [
              "string",
              "null"
            ]
          },
          "fielddata.evictions": {
            "type": [
              "string",
              "null"
            ]
          },
          "fe": {
            "type": [
              "string",
              "null"
            ]
          },
          "fielddataEvictions": {
            "type": [
              "string",
              "null"
            ]
          },
          "filter_cache.memory_size": {
            "type": [
              "string",
              "null"
            ]
          },
          "fcm": {
            "type": [
              "string",
              "null"
            ]
          },
          "filterCacheMemory": {
            "type": [
              "string",
              "null"
            ]
          },
          "filter_cache.evictions": {
            "type": [
              "string",
              "null"
            ]
          },
          "fce": {
            "type": [
              "string",
              "null"
            ]
          },
          "filterCacheEvictions": {
            "type": [
              "string",
              "null"
            ]
          },
          "flush.total": {
            "type": [
              "string",
              "null"
            ]
          },
          "ft": {
            "type": [
              "string",
              "null"
            ]
          },
          "flushTotal": {
            "type": [
              "string",
              "null"
            ]
          },
          "flush.total_time": {
            "type": [
              "string",
              "null"
            ]
          },
          "ftt": {
            "type": [
              "string",
              "null"
            ]
          },
          "flushTotalTime": {
            "type": [
              "string",
              "null"
            ]
          },
          "get.current": {
            "type": [
              "string",
              "null"
            ]
          },
          "gc": {
            "type": [
              "string",
              "null"
            ]
          },
          "getCurrent": {
            "type": [
              "string",
              "null"
            ]
          },
          "get.time": {
            "type": [
              "string",
              "null"
            ]
          },
          "gti": {
            "type": [
              "string",
              "null"
            ]
          },
          "getTime": {
            "type": [
              "string",
              "null"
            ]
          },
          "get.total": {
            "type": [
              "string",
              "null"
            ]
          },
          "gto": {
            "type": [
              "string",
              "null"
            ]
          },
          "getTotal": {
            "type": [
              "string",
              "null"
            ]
          },
          "get.exists_time": {
            "type": [
              "string",
              "null"
            ]
          },
          "geti": {
            "type": [
              "string",
              "null"
            ]
          },
          "getExistsTime": {
            "type": [
              "string",
              "null"
            ]
          },
          "get.exists_total": {
            "type": [
              "string",
              "null"
            ]
          },
          "geto": {
            "type": [
              "string",
              "null"
            ]
          },
          "getExistsTotal": {
            "type": [
              "string",
              "null"
            ]
          },
          "get.missing_time": {
            "type": [
              "string",
              "null"
            ]
          },
          "gmti": {
            "type": [
              "string",
              "null"
            ]
          },
          "getMissingTime": {
            "type": [
              "string",
              "null"
            ]
          },
          "get.missing_total": {
            "type": [
              "string",
              "null"
            ]
          },
          "gmto": {
            "type": [
              "string",
              "null"
            ]
          },
          "getMissingTotal": {
            "type": [
              "string",
              "null"
            ]
          },
          "id_cache.memory_size": {
            "type": [
              "string",
              "null"
            ]
          },
          "im": {
            "type": [
              "string",
              "null"
            ]
          },
          "idCacheMemory": {
            "type": [
              "string",
              "null"
            ]
          },
          "indexing.delete_current": {
            "type": [
              "string",
              "null"
            ]
          },
          "idc": {
            "type": [
              "string",
              "null"
            ]
          },
          "indexingDeleteCurrent": {
            "type": [
              "string",
              "null"
            ]
          },
          "indexing.delete_time": {
            "type": [
              "string",
              "null"
            ]
          },
          "idti": {
            "type": [
              "string",
              "null"
            ]
          },
          "indexingDeleteTime": {
            "type": [
              "string",
              "null"
            ]
          },
          "indexing.delete_total": {
            "type": [
              "string",
              "null"
            ]
          },
          "idto": {
            "type": [
              "string",
              "null"
            ]
          },
          "indexingDeleteTotal": {
            "type": [
              "string",
              "null"
            ]
          },
          "indexing.index_current": {
            "type": [
              "string",
              "null"
            ]
          },
          "iic": {
            "type": [
              "string",
              "null"
            ]
          },
          "indexingIndexCurrent": {
            "type": [
              "string",
              "null"
            ]
          },
          "indexing.index_time": {
            "type": [
              "string",
              "null"
            ]
          },
          "iiti": {
            "type": [
              "string",
              "null"
            ]
          },
          "indexingIndexTime": {
            "type": [
              "string",
              "null"
            ]
          },
          "indexing.index_total": {
            "type": [
              "string",
              "null"
            ]
          },
          "iito": {
            "type": [
              "string",
              "null"
            ]
          },
          "indexingIndexTotal": {
            "type": [
              "string",
              "null"
            ]
          },
          "merges.current": {
            "type": [
              "string",
              "null"
            ]
          },
          "mc": {
            "type": [
              "string",
              "null"
            ]
          },
          "mergesCurrent": {
            "type": [
              "string",
              "null"
            ]
          },
          "merges.current_docs": {
            "type": [
              "string",
              "null"
            ]
          },
          "mcd": {
            "type": [
              "string",
              "null"
            ]
          },
          "mergesCurrentDocs": {
            "type": [
              "string",
              "null"
            ]
          },
          "merges.current_size": {
            "type": [
              "string",
              "null"
            ]
          },
          "mcs": {
            "type": [
              "string",
              "null"
            ]
          },
          "mergesCurrentSize": {
            "type": [
              "string",
              "null"
            ]
          },
          "merges.total": {
            "type": [
              "string",
              "null"
            ]
          },
          "mt": {
            "type": [
              "string",
              "null"
            ]
          },
          "mergesTotal": {
            "type": [
              "string",
              "null"
            ]
          },
          "merges.total_docs": {
            "type": [
              "string",
              "null"
            ]
          },
          "mtd": {
            "type": [
              "string",
              "null"
            ]
          },
          "mergesTotalDocs": {
            "type": [
              "string",
              "null"
            ]
          },
          "merges.total_time": {
            "type": [
              "string",
              "null"
            ]
          },
          "mtt": {
            "type": [
              "string",
              "null"
            ]
          },
          "mergesTotalTime": {
            "type": [
              "string",
              "null"
            ]
          },
          "percolate.current": {
            "type": [
              "string",
              "null"
            ]
          },
          "pc": {
            "type": [
              "string",
              "null"
            ]
          },
          "percolateCurrent": {
            "type": [
              "string",
              "null"
            ]
          },
          "percolate.memory_size": {
            "type": [
              "string",
              "null"
            ]
          },
          "pm": {
            "type": [
              "string",
              "null"
            ]
          },
          "percolateMemory": {
            "type": [
              "string",
              "null"
            ]
          },
          "percolate.queries": {
            "type": [
              "string",
              "null"
            ]
          },
          "pq": {
            "type": [
              "string",
              "null"
            ]
          },
          "percolateQueries": {
            "type": [
              "string",
              "null"
            ]
          },
          "percolate.time": {
            "type": [
              "string",
              "null"
            ]
          },
          "pti": {
            "type": [
              "string",
              "null"
            ]
          },
          "percolateTime": {
            "type": [
              "string",
              "null"
            ]
          },
          "percolate.total": {
            "type": [
              "string",
              "null"
            ]
          },
          "pto": {
            "type": [
              "string",
              "null"
            ]
          },
          "percolateTotal": {
            "type": [
              "string",
              "null"
            ]
          },
          "refresh.total": {
            "type": [
              "string",
              "null"
            ]
          },
          "rto": {
            "type": [
              "string",
              "null"
            ]
          },
          "refreshTotal": {
            "type": [
              "string",
              "null"
            ]
          },
          "refresh.time": {
            "type": [
              "string",
              "null"
            ]
          },
          "rti": {
            "type": [
              "string",
              "null"
            ]
          },
          "refreshTime": {
            "type": [
              "string",
              "null"
            ]
          },
          "search.fetch_current": {
            "type": [
              "string",
              "null"
            ]
          },
          "sfc": {
            "type": [
              "string",
              "null"
            ]
          },
          "searchFetchCurrent": {
            "type": [
              "string",
              "null"
            ]
          },
          "search.fetch_time": {
            "type": [
              "string",
              "null"
            ]
          },
          "sfti": {
            "type": [
              "string",
              "null"
            ]
          },
          "searchFetchTime": {
            "type": [
              "string",
              "null"
            ]
          },
          "search.fetch_total": {
            "type": [
              "string",
              "null"
            ]
          },
          "sfto": {
            "type": [
              "string",
              "null"
            ]
          },
          "searchFetchTotal": {
            "type": [
              "string",
              "null"
            ]
          },
          "search.open_contexts": {
            "type": [
              "string",
              "null"
            ]
          },
          "so": {
            "type": [
              "string",
              "null"
            ]
          },
          "searchOpenContexts": {
            "type": [
              "string",
              "null"
            ]
          },
          "search.query_current": {
            "type": [
              "string",
              "null"
            ]
          },
          "sqc": {
            "type": [
              "string",
              "null"
            ]
          },
          "searchQueryCurrent": {
            "type": [
              "string",
              "null"
            ]
          },
          "search.query_time": {
            "type": [
              "string",
              "null"
            ]
          },
          "sqti": {
            "type": [
              "string",
              "null"
            ]
          },
          "searchQueryTime": {
            "type": [
              "string",
              "null"
            ]
          },
          "search.query_total": {
            "type": [
              "string",
              "null"
            ]
          },
          "sqto": {
            "type": [
              "string",
              "null"
            ]
          },
          "searchQueryTotal": {
            "type": [
              "string",
              "null"
            ]
          },
          "segments.count": {
            "type": [
              "string",
              "null"
            ]
          },
          "sc": {
            "type": [
              "string",
              "null"
            ]
          },
          "segmentsCount": {
            "type": [
              "string",
              "null"
            ]
          },
          "segments.memory": {
            "type": [
              "string",
              "null"
            ]
          },
          "sm": {
            "type": [
              "string",
              "null"
            ]
          },
          "segmentsMemory": {
            "type": [
              "string",
              "null"
            ]
          },
          "segments.index_writer_memory": {
            "type": [
              "string",
              "null"
            ]
          },
          "siwm": {
            "type": [
              "string",
              "null"
            ]
          },
          "segmentsIndexWriterMemory": {
            "type": [
              "string",
              "null"
            ]
          },
          "segments.index_writer_max_memory": {
            "type": [
              "string",
              "null"
            ]
          },
          "siwmx": {
            "type": [
              "string",
              "null"
            ]
          },
          "segmentsIndexWriterMaxMemory": {
            "type": [
              "string",
              "null"
            ]
          },
          "segments.version_map_memory": {
            "type": [
              "string",
              "null"
            ]
          },
          "svmm": {
            "type": [
              "string",
              "null"
            ]
          },
          "segmentsVersionMapMemory": {
            "type": [
              "string",
              "null"
            ]
          }
        },
        "required": [
          "id",
          "nodeId",
          "pid",
          "p",
          "host",
          "h",
          "ip",
          "i",
          "port",
          "po",
          "version",
          "v",
          "build",
          "b",
          "jdk",
          "j",
          "disk.avail",
          "d",
          "disk",
          "diskAvail",
          "heap.percent",
          "hp",
          "heapPercent",
          "heap.max",
          "hm",
          "heapMax",
          "ram.percent",
          "rp",
          "ramPercent",
          "ram.max",
          "rm",
          "ramMax",
          "load",
          "l",
          "uptime",
          "u",
          "node.role",
          "r",
          "dc",
          "data/client",
          "nodeRole",
          "master",
          "m",
          "name",
          "n",
          "completion.size",
          "cs",
          "completionSize",
          "fielddata.memory_size",
          "fm",
          "fielddataMemory",
          "fielddata.evictions",
          "fe",
          "fielddataEvictions",
          "filter_cache.memory_size",
          "fcm",
          "filterCacheMemory",
          "filter_cache.evictions",
          "fce",
          "filterCacheEvictions",
          "flush.total",
          "ft",
          "flushTotal",
          "flush.total_time",
          "ftt",
          "flushTotalTime",
          "get.current",
          "gc",
          "getCurrent",
          "get.time",
          "gti",
          "getTime",
          "get.total",
          "gto",
          "getTotal",
          "get.exists_time",
          "geti",
          "getExistsTime",
          "get.exists_total",
          "geto",
          "getExistsTotal",
          "get.missing_time",
          "gmti",
          "getMissingTime",
          "get.missing_total",
          "gmto",
          "getMissingTotal",
          "id_cache.memory_size",
          "im",
          "idCacheMemory",
          "indexing.delete_current",
          "idc",
          "indexingDeleteCurrent",
          "indexing.delete_time",
          "idti",
          "indexingDeleteTime",
          "indexing.delete_total",
          "idto",
          "indexingDeleteTotal",
          "indexing.index_current",
          "iic",
          "indexingIndexCurrent",
          "indexing.index_time",
          "iiti",
          "indexingIndexTime",
          "indexing.index_total",
          "iito",
          "indexingIndexTotal",
          "merges.current",
          "mc",
          "mergesCurrent",
          "merges.current_docs",
          "mcd",
          "mergesCurrentDocs",
          "merges.current_size",
          "mcs",
          "mergesCurrentSize",
          "merges.total",
          "mt",
          "mergesTotal",
          "merges.total_docs",
          "mtd",
          "mergesTotalDocs",
          "merges.total_time",
          "mtt",
          "mergesTotalTime",
          "percolate.current",
          "pc",
          "percolateCurrent",
          "percolate.memory_size",
          "pm",
          "percolateMemory",
          "percolate.queries",
          "pq",
          "percolateQueries",
          "percolate.time",
          "pti",
          "percolateTime",
          "percolate.total",
          "pto",
          "percolateTotal",
          "refresh.total",
          "rto",
          "refreshTotal",
          "refresh.time",
          "rti",
          "refreshTime",
          "search.fetch_current",
          "sfc",
          "searchFetchCurrent",
          "search.fetch_time",
          "sfti",
          "searchFetchTime",
          "search.fetch_total",
          "sfto",
          "searchFetchTotal",
          "search.open_contexts",
          "so",
          "searchOpenContexts",
          "search.query_current",
          "sqc",
          "searchQueryCurrent",
          "search.query_time",
          "sqti",
          "searchQueryTime",
          "search.query_total",
          "sqto",
          "searchQueryTotal",
          "segments.count",
          "sc",
          "segmentsCount",
          "segments.memory",
          "sm",
          "segmentsMemory",
          "segments.index_writer_memory",
          "siwm",
          "segmentsIndexWriterMemory",
          "segments.index_writer_max_memory",
          "siwmx",
          "segmentsIndexWriterMaxMemory",
          "segments.version_map_memory",
          "svmm",
          "segmentsVersionMapMemory"
        ]
      }
    }
  },
  "required": [
    "records"
  ]
}