{
  "id": "Nest.ICatResponse`1[[Nest.CatRecoveryRecord, Nest, Version=1.0.0.0, Culture=neutral, PublicKeyToken=null]]",
  "$schema": "http://json-schema.org/draft-04/schema#",
  "title": "ICatResponse`1",
  "type": "object",
  "properties": {
    "records": {
      "id": "System.Collections.Generic.IEnumerable`1[[Nest.CatRecoveryRecord, Nest, Version=1.0.0.0, Culture=neutral, PublicKeyToken=null]]",
      "type": [
        "array",
        "null"
      ],
      "items": {
        "id": "Nest.CatRecoveryRecord",
        "type": [
          "object",
          "null"
        ],
        "properties": {
          "shard": {
            "type": [
              "string",
              "null"
            ]
          },
          "time": {
            "type": [
              "string",
              "null"
            ]
          },
          "type": {
            "type": [
              "string",
              "null"
            ]
          },
          "stage": {
            "type": [
              "string",
              "null"
            ]
          },
          "source_host": {
            "type": [
              "string",
              "null"
            ]
          },
          "target_host": {
            "type": [
              "string",
              "null"
            ]
          },
          "repository": {
            "type": [
              "string",
              "null"
            ]
          },
          "snapshot": {
            "type": [
              "string",
              "null"
            ]
          },
          "files": {
            "type": [
              "string",
              "null"
            ]
          },
          "files_percent": {
            "type": [
              "string",
              "null"
            ]
          },
          "bytes": {
            "type": [
              "string",
              "null"
            ]
          },
          "bytes_percent": {
            "type": [
              "string",
              "null"
            ]
          }
        },
        "required": [
          "shard",
          "time",
          "type",
          "stage",
          "source_host",
          "target_host",
          "repository",
          "snapshot",
          "files",
          "files_percent",
          "bytes",
          "bytes_percent"
        ]
      }
    }
  },
  "required": [
    "records"
  ]
}